epist_mcp_server/__init__.py
epist_mcp_server/server.py
epist_mcp_server-0.1.0.dist-info/METADATA
epist_mcp_server-0.1.0.dist-info/WHEEL
epist_mcp_server-0.1.0.dist-info/entry_points.txt
epist_mcp_server-0.1.0.dist-info/RECORD
