Metadata-Version: 2.4
Name: epist-mcp-server
Version: 0.1.0
Summary: MCP Server for Epist.ai Audio Knowledge Base
Project-URL: Homepage, https://epist.ai
Project-URL: Repository, https://github.com/epist-ai/epist-mcp-server
Author-email: Epist Team <support@epist.ai>
Requires-Python: >=3.10
Requires-Dist: httpx
Requires-Dist: mcp
